scellop/__init__.py
scellop/static/widget.css
scellop/static/widget.js
scellop-1.0.0.dist-info/METADATA
scellop-1.0.0.dist-info/WHEEL
scellop-1.0.0.dist-info/RECORD
