Metadata-Version: 2.4
Name: scellop
Version: 1.0.0
Requires-Dist: anndata
Requires-Dist: anywidget
Requires-Dist: pandas
Provides-Extra: dev
Requires-Dist: jupyterlab; extra == 'dev'
Requires-Dist: watchfiles; extra == 'dev'
